{
    "allowProxyFor" : [
        "adelaidecitycouncil.com",
        "aemo.com.au",
        "aodn.org.au",
        "arcgis.com",
        "argo.jcommops.org",
        "aurin.org.au",
        "csiro.au",
        "gov.au",
        "mapsengine.google.com",
        "nasa.gov",
        "nci.org.au",
        "nicta.com.au",
        "noaa.gov",
        "s3-ap-southeast-2.amazonaws.com",
        "www.abc.net.au",
        "www.dptiapps.com.au",
        "www.googleapis.com"
    ],
    "feedback": {
        "userAgent": "TerriaBot (TerriaJS Feedback)",
        "issuesUrl": "https://api.github.com/repos/TerriaJS/NationalMap-Feedback/issues",
        "accessToken": "FEEDBACK_ACCESS_TOKEN"
    },
    "trustProxy": true
}
